graphsignal/__init__.py
graphsignal/__main__.py
graphsignal/client/__init__.py
graphsignal/client/api/__init__.py
graphsignal/client/api/default_api.py
graphsignal/client/api_client.py
graphsignal/client/api_response.py
graphsignal/client/configuration.py
graphsignal/client/exceptions.py
graphsignal/client/models/__init__.py
graphsignal/client/models/attribute.py
graphsignal/client/models/counter.py
graphsignal/client/models/error.py
graphsignal/client/models/error_query_result.py
graphsignal/client/models/histogram.py
graphsignal/client/models/http_validation_error.py
graphsignal/client/models/log_entry.py
graphsignal/client/models/metric.py
graphsignal/client/models/metric_type.py
graphsignal/client/models/profile.py
graphsignal/client/models/profile_query_result.py
graphsignal/client/models/span.py
graphsignal/client/models/span_query_result.py
graphsignal/client/models/summary.py
graphsignal/client/models/tag.py
graphsignal/client/models/validation_error.py
graphsignal/client/models/validation_error_loc_inner.py
graphsignal/client/py.typed
graphsignal/client/rest.py
graphsignal/env_vars.py
graphsignal/logs.py
graphsignal/metrics.py
graphsignal/recorders/__init__.py
graphsignal/recorders/base_recorder.py
graphsignal/recorders/exception_recorder.py
graphsignal/recorders/instrumentation.py
graphsignal/recorders/nvml_recorder.py
graphsignal/recorders/otel_adapter.py
graphsignal/recorders/otel_collector.py
graphsignal/recorders/process_recorder.py
graphsignal/recorders/profiler_utils.py
graphsignal/recorders/prometheus_adapter.py
graphsignal/recorders/python_recorder.py
graphsignal/recorders/pytorch_recorder.py
graphsignal/recorders/vllm_recorder.py
graphsignal/spans.py
graphsignal/tracer.py
graphsignal/uploader.py
graphsignal/utils.py
graphsignal/version.py
graphsignal-0.18.4.dist-info/METADATA
graphsignal-0.18.4.dist-info/WHEEL
graphsignal-0.18.4.dist-info/entry_points.txt
graphsignal-0.18.4.dist-info/licenses/LICENSE
graphsignal-0.18.4.dist-info/licenses/NOTICE
graphsignal-0.18.4.dist-info/RECORD
