Metadata-Version: 2.4
Name: graphsignal
Version: 0.18.4
Summary: Graphsignal Tracer for Python
License: Apache-2.0
License-File: LICENSE
License-File: NOTICE
Keywords: LLM observability,LLM analytics,Agent observability,Agent analytics
Author: Graphsignal, Inc.
Author-email: devops@graphsignal.com
Requires-Python: >=3.9,<4
Classifier: Development Status :: 5 - Production/Stable
Classifier: Intended Audience :: Developers
Classifier: Intended Audience :: Science/Research
Classifier: License :: OSI Approved :: Apache Software License
Classifier: Operating System :: OS Independent
Classifier: Programming Language :: Python
Classifier: Programming Language :: Python :: 3
Classifier: Programming Language :: Python :: 3.9
Classifier: Programming Language :: Python :: 3.10
Classifier: Programming Language :: Python :: 3.11
Classifier: Programming Language :: Python :: 3.12
Classifier: Programming Language :: Python :: 3.13
Classifier: Programming Language :: Python :: 3.14
Classifier: Topic :: Scientific/Engineering
Classifier: Topic :: Scientific/Engineering :: Artificial Intelligence
Classifier: Topic :: Software Development
Classifier: Topic :: System :: Monitoring
Requires-Dist: grpcio
Requires-Dist: nvidia-ml-py (>=12)
Requires-Dist: opentelemetry-api
Requires-Dist: opentelemetry-exporter-otlp
Requires-Dist: opentelemetry-proto
Requires-Dist: opentelemetry-sdk
Requires-Dist: opentelemetry-semantic-conventions-ai
Requires-Dist: pydantic (>2)
Requires-Dist: python-dateutil
Requires-Dist: typing-extensions (>4.7.1)
Requires-Dist: urllib3 (>=1.25.3,<2.1.0)
Project-URL: Homepage, https://graphsignal.com
Project-URL: Repository, https://graphsignal.com
